cpu/hack/spif/spirom.v
module spirom (
    input clk,
    output reg mosi = 0,
    output reg sck = 0,
    output reg cs = 1  // active low
);

  localparam WAIT = 4;

  reg [4:0] state = 0;
  integer wait_counter = 0;

  localparam INIT = 0;
  localparam SEND_CMD = 1;

  // initial begin
  //   $monitor(mosi);
  // end

  // reg [7:0] command = 8'h03;
  reg [7:0] command = 8'b11010010;

  always @(posedge clk) begin
    case (state)
      INIT: begin
        if (wait_counter < WAIT) begin
          wait_counter <= wait_counter + 1;
        end else begin
          state <= SEND_CMD;
        end
      end
      SEND_CMD: begin
        cs <= 0;  // set cs
        sck <= ~sck;  // toggle clock
        mosi <= command[7];  // push command bit out
        command <= command << 1;  // shift command
      end

    endcase

  end

endmodule

cpu/hack/spif/spirom_tb.v
module spirom_tb;
  reg  clk = 0;
  wire mosi;
  wire sck;
  wire cs;

  spirom u0 (
      clk,
      mosi,
      sck,
      cs
  );

  always begin
    #2 clk = ~clk;
  end

  initial begin
    $monitor("%b", mosi);

    $dumpfile("spirom.vcd");
    $dumpvars(0, spirom_tb);

    #50 $finish;
  end


endmodule

cpu/hack/spif/spirom.vcd
$date
	Thu Jul 27 00:58:59 2023
$end
$version
	Icarus Verilog
$end
$timescale
	1s
$end
$scope module spirom_tb $end
$var wire 1 ! sck $end
$var wire 1 " mosi $end
$var wire 1 # cs $end
$var reg 1 $ clk $end
$scope module u0 $end
$var wire 1 $ clk $end
$var parameter 32 % INIT $end
$var parameter 32 & SEND_CMD $end
$var parameter 32 ' WAIT $end
$var reg 8 ( command [7:0] $end
$var reg 1 # cs $end
$var reg 1 " mosi $end
$var reg 1 ! sck $end
$var reg 5 ) state [4:0] $end
$var integer 32 * wait_counter [31:0] $end
$upscope $end
$upscope $end
$enddefinitions $end
$comment Show the parameter values. $end
$dumpall
b100 '
b1 &
b0 %
$end
#0
$dumpvars
b0 *
b0 )
b11010010 (
0$
1#
0"
0!
$end
#2
b1 *
1$
#4
0$
#6
b10 *
1$
#8
0$
#10
b11 *
1$
#12
0$
#14
b100 *
1$
#16
0$
#18
b1 )
1$
#20
0$
#22
b10100100 (
1"
1!
0#
1$
#24
0$
#26
b1001000 (
0!
1$
#28
0$
#30
b10010000 (
0"
1!
1$
#32
0$
#34
b100000 (
1"
0!
1$
#36
0$
#38
b1000000 (
0"
1!
1$
#40
0$
#42
b10000000 (
0!
1$
#44
0$
#46
b0 (
1"
1!
1$
#48
0$
#50
0"
0!
1$
