cpu_16bit/hack.v
module hack (
    input clk,
    input [15:0] instr,

    output reg [14:0] PC
);
  reg [15:0] A;
  reg [15:0] D;

  reg [15:0] mem[7:0];

  reg [15:0] ALU;

  // ac bit, determines whether a-ins or c-ins
  wire ac = instr[15];

  // the 15-bit value to be loaded to A, if a-ins
  wire [14:0] v = instr[14:0];

  // "a" bit, source of Y operand of alu
  wire a = instr[12];
  // 6-bit c's
  wire [5:0] c = instr[11:6];
  // 3-bit d
  wire [2:0] dest = instr[5:3];
  // 3-bit j
  wire [2:0] jump = instr[2:0];

  // comp, concat a with c's to form a single table like in wiki
  wire [6:0] comp = {a, c};

  wire [15:0] M = mem[A];  // M "register"

  initial begin
    A = 0;
    D = 0;

    // $monitor("A:%d | D:%d", A, D);
    $monitor("%h", mem[2]);
  end

  always @(posedge clk) begin

    if (ac == 1'b0) begin
      // a-instruction
      // load v into A register
      A = v;
    end else if (ac == 1'b1) begin
      // c-instruction

      // comp, alu output
      case (comp)
        7'b0101010: ALU = 0;
        7'b0111111: ALU = 1;
        7'b0111010: ALU = -1;
        7'b0001100: ALU = D;
        7'b0110000: ALU = A;
        7'b1110000: ALU = M;
        7'b0001101: ALU = !D;
        7'b0110001: ALU = !A;
        7'b1110001: ALU = !M;
        7'b0001111: ALU = -D;
        7'b0110011: ALU = -A;
        7'b1110011: ALU = -M;
        7'b0011111: ALU = D + 1;
        7'b0110111: ALU = A + 1;
        7'b1110111: ALU = M + 1;
        7'b0001110: ALU = D - 1;
        7'b0110010: ALU = A - 1;
        7'b1110010: ALU = M - 1;
        7'b0000010: ALU = D + A;
        7'b1000010: ALU = D + M;
        7'b0010011: ALU = D - A;
        7'b1010011: ALU = D - M;
        7'b0000111: ALU = A - D;
        7'b1000111: ALU = M - D;
        7'b0000000: ALU = D & A;
        7'b1000000: ALU = D & M;
        7'b0010101: ALU = D | A;
        7'b1010101: ALU = D | M;

        default: ALU = 0;

      endcase

      // dest, where to store this alu output
      case (dest)
        3'b000:  ;
        3'b001:  mem[A] = ALU;
        3'b010:  D = ALU;
        3'b011: begin
          D = ALU;
          mem[A] = ALU;
        end
        3'b100:  A = ALU;
        3'b101: begin
          A = ALU;
          mem[A] = ALU;
        end
        3'b110: begin
          A = ALU;
          D = ALU;
        end
        3'b111: begin
          A = ALU;
          D = ALU;
          mem[A] = ALU;
        end
        default: ;

      endcase

      // if conditions are satisfied, we "jump" wherever A points to
      case (jump)
        // no jump
        3'b000:  PC = PC + 1;
        // jump if comp > 0
        3'b001:  PC = (ALU > 0) ? A : PC + 1;
        3'b010:  PC = (ALU == 0) ? A : PC + 1;
        3'b011:  PC = (ALU >= 0) ? A : PC + 1;
        3'b100:  PC = (ALU < 0) ? A : PC + 1;
        3'b101:  PC = (ALU != 0) ? A : PC + 1;
        3'b110:  PC = (ALU <= 0) ? A : PC + 1;
        // unconditional jump
        3'b111:  PC = A;
        default: PC = PC + 1;
      endcase

    end

  end

endmodule

cpu_16bit/hack_tb.v
module hack_tb;

  reg clk;
  reg [15:0] instr;

  hack h0 (
      clk,
      instr
  );

  initial begin
    clk = 0;
    //$monitor("%b", instr);

  end

  always #1 clk = ~clk;

  initial begin
    #2 instr = 16'h0003;
    #2 instr = 16'hEC10;
    #2 instr = 16'h0000;
    #2 instr = 16'hE308;
    #2 instr = 16'h0004;
    #2 instr = 16'hEC10;
    #2 instr = 16'h0001;
    #2 instr = 16'hE308;
    #2 instr = 16'h0000;
    #2 instr = 16'hFC10;
    #2 instr = 16'h0001;
    #2 instr = 16'hF090;
    #2 instr = 16'h0002;
    #2 instr = 16'hE308;
    #2 instr = 16'h0000;
    #2 $finish;
  end

  initial begin
    $dumpfile("hack.vcd");
    $dumpvars(0, hack_tb);
  end
endmodule

cpu_16bit/hack.vcd
$date
	Mon Jul 24 22:09:53 2023
$end
$version
	Icarus Verilog
$end
$timescale
	1s
$end
$scope module hack_tb $end
$var reg 1 ! clk $end
$var reg 16 " instr [15:0] $end
$scope module h0 $end
$var wire 16 # M [15:0] $end
$var wire 1 ! clk $end
$var wire 16 $ instr [15:0] $end
$var wire 15 % v [14:0] $end
$var wire 3 & jump [2:0] $end
$var wire 3 ' dest [2:0] $end
$var wire 7 ( comp [6:0] $end
$var wire 6 ) c [5:0] $end
$var wire 1 * ac $end
$var wire 1 + a $end
$var reg 16 , A [15:0] $end
$var reg 16 - ALU [15:0] $end
$var reg 16 . D [15:0] $end
$var reg 15 / PC [14:0] $end
$upscope $end
$upscope $end
$enddefinitions $end
$comment Show the parameter values. $end
$dumpall
$end
#0
$dumpvars
bx /
b0 .
bx -
b0 ,
x+
x*
bx )
bx (
bx '
bx &
bx %
bx $
bx #
bx "
0!
$end
#1
1!
#2
0*
b11 %
0+
b0 (
b0 )
b0 '
b11 &
0!
b11 "
b11 $
#3
b11 ,
1!
#4
1*
b110110000010000 %
b110000 (
b110000 )
b10 '
b0 &
0!
b1110110000010000 "
b1110110000010000 $
#5
b11 .
b11 -
1!
#6
0*
b0 %
b0 (
b0 )
b0 '
0!
b0 "
b0 $
#7
b0 ,
1!
#8
1*
b110001100001000 %
b1100 (
b1100 )
b1 '
0!
b1110001100001000 "
b1110001100001000 $
#9
b11 #
1!
#10
0*
b100 %
b0 (
b0 )
b0 '
b100 &
0!
b100 "
b100 $
#11
bx #
b100 ,
1!
#12
1*
b110110000010000 %
b110000 (
b110000 )
b10 '
b0 &
0!
b1110110000010000 "
b1110110000010000 $
#13
b100 .
b100 -
1!
#14
0*
b1 %
b0 (
b0 )
b0 '
b1 &
0!
b1 "
b1 $
#15
b1 ,
1!
#16
1*
b110001100001000 %
b1100 (
b1100 )
b1 '
b0 &
0!
b1110001100001000 "
b1110001100001000 $
#17
b100 #
1!
#18
0*
b0 %
b0 (
b0 )
b0 '
0!
b0 "
b0 $
#19
b11 #
b0 ,
1!
#20
1*
b111110000010000 %
1+
b1110000 (
b110000 )
b10 '
0!
b1111110000010000 "
b1111110000010000 $
#21
b11 .
b11 -
1!
#22
0*
b1 %
0+
b0 (
b0 )
b0 '
b1 &
0!
b1 "
b1 $
#23
b100 #
b1 ,
1!
#24
1*
b111000010010000 %
1+
b1000010 (
b10 )
b10 '
b0 &
0!
b1111000010010000 "
b1111000010010000 $
#25
b111 .
b111 -
1!
#26
0*
b10 %
0+
b0 (
b0 )
b0 '
b10 &
0!
b10 "
b10 $
#27
bx #
b10 ,
1!
#28
1*
b110001100001000 %
b1100 (
b1100 )
b1 '
b0 &
0!
b1110001100001000 "
b1110001100001000 $
#29
b111 #
1!
#30
0*
b0 %
b0 (
b0 )
b0 '
0!
b0 "
b0 $
#31
b11 #
b0 ,
1!
