cpu/hack/cpu.v
/*
 * Generated by Digital. Don't modify this file!
 * Any changes will be lost if this file is regenerated.
 */

module computer (
    input clk,
    output [15:0] SCREEN
);
  wire [14:0] s0;
  wire [15:0] s1;
  // ROM32K
  DIG_ROM_32768X16_ROM32K DIG_ROM_32768X16_ROM32K_i0 (
      .A  (s0),
      .sel(1'b1),
      .D  (s1)
  );
  // hack
  hack hack_i1 (
      .instr(s1),
      .clk(clk),
      .PC(s0),
      .SCREEN(SCREEN)
  );
endmodule

module DIG_ROM_32768X16_ROM32K (
    input [14:0] A,
    input sel,
    output reg [15:0] D
);
  reg [15:0] my_rom[0:25];

  always @(*) begin
    if (~sel) D = 16'hz;
    else if (A > 15'h19) D = 16'h0;
    else D = my_rom[A];
  end

  initial begin
    my_rom[0]  = 16'h10;
    my_rom[1]  = 16'hefc8;
    my_rom[2]  = 16'h11;
    my_rom[3]  = 16'hefc8;
    my_rom[4]  = 16'h12;
    my_rom[5]  = 16'hea88;
    my_rom[6]  = 16'h10;
    my_rom[7]  = 16'hfc10;
    my_rom[8]  = 16'h4000;
    my_rom[9]  = 16'he308;
    my_rom[10] = 16'h10;
    my_rom[11] = 16'hfc10;
    my_rom[12] = 16'h11;
    my_rom[13] = 16'hf090;
    my_rom[14] = 16'h12;
    my_rom[15] = 16'he308;
    my_rom[16] = 16'h10;
    my_rom[17] = 16'hfc10;
    my_rom[18] = 16'h11;
    my_rom[19] = 16'he308;
    my_rom[20] = 16'h12;
    my_rom[21] = 16'hfc10;
    my_rom[22] = 16'h10;
    my_rom[23] = 16'he308;
    my_rom[24] = 16'h6;
    my_rom[25] = 16'hea87;
  end
endmodule

module hack (
    input [15:0] instr,
    input clk,

    output reg [14:0] PC,
    output [15:0] SCREEN
);
  reg [15:0] A;
  reg [15:0] D;

  reg [15:0] RAM[24576:0];

  reg signed [15:0] ALU;

  // ac bit, determines whether a-ins or c-ins
  wire ac = instr[15];

  // the 15-bit value to be loaded to A, if a-ins
  wire [14:0] v = instr[14:0];

  // "a" bit, source of Y operand of alu
  wire a = instr[12];
  // 6-bit c's
  wire [5:0] c = instr[11:6];
  // 3-bit d
  wire [2:0] dest = instr[5:3];
  // 3-bit j
  wire [2:0] jump = instr[2:0];

  // comp, concat a with c's to form a single table like in wiki
  wire [6:0] comp = {a, c};

  wire [15:0] M = RAM[A];  // M "register"

  assign SCREEN = RAM[16384];  // so R16 is "displayed"


  initial begin
    A  = 0;
    D  = 0;
    PC = 0;

    // $monitor("A:%d | D:%d", A, D);

    //$monitor("%d", SCREEN);
  end


  always @(posedge clk) begin

    if (ac == 1'b0) begin
      // a-instruction
      // load v into A register
      A  = v;
      PC = PC + 1;
    end else if (ac == 1'b1) begin
      // c-instruction

      // comp, alu output
      case (comp)
        7'b0101010: ALU = 0;
        7'b0111111: ALU = 1;
        7'b0111010: ALU = -1;
        7'b0001100: ALU = D;
        7'b0110000: ALU = A;
        7'b1110000: ALU = M;
        7'b0001101: ALU = !D;
        7'b0110001: ALU = !A;
        7'b1110001: ALU = !M;
        7'b0001111: ALU = -D;
        7'b0110011: ALU = -A;
        7'b1110011: ALU = -M;
        7'b0011111: ALU = D + 1;
        7'b0110111: ALU = A + 1;
        7'b1110111: ALU = M + 1;
        7'b0001110: ALU = D - 1;
        7'b0110010: ALU = A - 1;
        7'b1110010: ALU = M - 1;
        7'b0000010: ALU = D + A;
        7'b1000010: ALU = D + M;
        7'b0010011: ALU = D - A;
        7'b1010011: ALU = D - M;
        7'b0000111: ALU = A - D;
        7'b1000111: ALU = M - D;
        7'b0000000: ALU = D & A;
        7'b1000000: ALU = D & M;
        7'b0010101: ALU = D | A;
        7'b1010101: ALU = D | M;

        default: ALU = 0;

      endcase

      // dest, where to store this alu output
      case (dest)
        3'b000:  ;
        3'b001:  RAM[A] = ALU;
        3'b010:  D = ALU;
        3'b011: begin
          D = ALU;
          RAM[A] = ALU;
        end
        3'b100:  A = ALU;
        3'b101: begin
          A = ALU;
          RAM[A] = ALU;
        end
        3'b110: begin
          A = ALU;
          D = ALU;
        end
        3'b111: begin
          A = ALU;
          D = ALU;
          RAM[A] = ALU;
        end
        default: ;

      endcase

      // if conditions are satisfied, we "jump" wherever A points to
      case (jump)
        // no jump
        3'b000:  PC = PC + 1;
        // jump if comp > 0
        3'b001:  PC = (ALU > 0) ? A : PC + 1;
        3'b010:  PC = (ALU == 0) ? A : PC + 1;
        3'b011:  PC = (ALU >= 0) ? A : PC + 1;
        3'b100:  PC = (ALU < 0) ? A : PC + 1;
        3'b101:  PC = (ALU != 0) ? A : PC + 1;
        3'b110:  PC = (ALU <= 0) ? A : PC + 1;
        // unconditional jump
        3'b111:  PC = A;
        default: PC = PC + 1;
      endcase

    end

  end

endmodule

cpu_16bit/hack/hack_tb.v
module hack_tb;

  reg clk;
  reg [15:0] instr;
  wire [14:0] PC;
  wire [15:0] SCREEN;

  // ROM
  reg [15:0] ROM[0:255];

  initial begin
    $readmemh("fib.hex", ROM);
    #2 clk = 0;
    $monitor("%d", SCREEN);

    for (integer i = 0; i < 1000; i++) begin
      #1 clk = ~clk;
      instr = ROM[PC];
    end

    #2 $finish;

  end

  hack h0 (
      instr,
      clk,
      PC,
      SCREEN
  );

  initial begin
    $dumpfile("hack.vcd");
    $dumpvars(0, hack_tb);
  end
endmodule

cpu/hack/hack.vcd
$date
	Wed Jul 26 20:09:48 2023
$end
$version
	Icarus Verilog
$end
$timescale
	1s
$end
$scope module hack_tb $end
$var wire 16 ! SCREEN [15:0] $end
$var wire 15 " PC [14:0] $end
$var reg 1 # clk $end
$var reg 16 $ instr [15:0] $end
$scope module h0 $end
$var wire 16 % M [15:0] $end
$var wire 16 & SCREEN [15:0] $end
$var wire 1 # clk $end
$var wire 16 ' instr [15:0] $end
$var wire 15 ( v [14:0] $end
$var wire 3 ) jump [2:0] $end
$var wire 3 * dest [2:0] $end
$var wire 7 + comp [6:0] $end
$var wire 6 , c [5:0] $end
$var wire 1 - ac $end
$var wire 1 . a $end
$var reg 16 / A [15:0] $end
$var reg 16 0 ALU [15:0] $end
$var reg 16 1 D [15:0] $end
$var reg 15 2 PC [14:0] $end
$upscope $end
$scope begin $ivl_for_loop0 $end
$var integer 32 3 i [31:0] $end
$upscope $end
$upscope $end
$enddefinitions $end
$comment Show the parameter values. $end
$dumpall
$end
#0
$dumpvars
bx 3
b0 2
b0 1
bx 0
b0 /
x.
x-
bx ,
bx +
bx *
bx )
bx (
bx '
bx &
bx %
bx $
x#
b0 "
bx !
$end
#2
b0 3
0#
#3
0-
b10000 (
0.
b0 +
b0 ,
b10 *
b0 )
b1 3
b10000 $
b10000 '
1#
#4
b10 3
0#
#5
b1 "
b1 2
b10000 /
b11 3
1#
#6
1-
b110111111001000 (
b111111 +
b111111 ,
b1 *
b100 3
b1110111111001000 $
b1110111111001000 '
0#
#7
b10 "
b10 2
b1 %
b1 0
b101 3
1#
#8
0-
b10001 (
b0 +
b0 ,
b10 *
b1 )
b110 3
b10001 $
b10001 '
0#
#9
b11 "
b11 2
bx %
b10001 /
b111 3
1#
#10
1-
b110111111001000 (
b111111 +
b111111 ,
b1 *
b0 )
b1000 3
b1110111111001000 $
b1110111111001000 '
0#
#11
b100 "
b100 2
b1 %
b1001 3
1#
#12
0-
b10010 (
b0 +
b0 ,
b10 *
b10 )
b1010 3
b10010 $
b10010 '
0#
#13
b101 "
b101 2
bx %
b10010 /
b1011 3
1#
#14
1-
b110101010001000 (
b101010 +
b101010 ,
b1 *
b0 )
b1100 3
b1110101010001000 $
b1110101010001000 '
0#
#15
b110 "
b110 2
b0 %
b0 0
b1101 3
1#
#16
0-
b10000 (
b0 +
b0 ,
b10 *
b1110 3
b10000 $
b10000 '
0#
#17
b111 "
b111 2
b1 %
b10000 /
b1111 3
1#
#18
1-
b111110000010000 (
1.
b1110000 +
b110000 ,
b10000 3
b1111110000010000 $
b1111110000010000 '
0#
#19
b1000 "
b1000 2
b1 1
b1 0
b10001 3
1#
#20
0-
b100000000000000 (
0.
b0 +
b0 ,
b0 *
b10010 3
b100000000000000 $
b100000000000000 '
0#
#21
b1001 "
b1001 2
bx %
b100000000000000 /
b10011 3
1#
#22
1-
b110001100001000 (
b1100 +
b1100 ,
b1 *
b10100 3
b1110001100001000 $
b1110001100001000 '
0#
#23
b1010 "
b1010 2
b1 %
b1 !
b1 &
b10101 3
1#
#24
0-
b10000 (
b0 +
b0 ,
b10 *
b10110 3
b10000 $
b10000 '
0#
#25
b1011 "
b1011 2
b10000 /
b10111 3
1#
#26
1-
b111110000010000 (
1.
b1110000 +
b110000 ,
b11000 3
b1111110000010000 $
b1111110000010000 '
0#
#27
b1100 "
b1100 2
b11001 3
1#
#28
0-
b10001 (
0.
b0 +
b0 ,
b1 )
b11010 3
b10001 $
b10001 '
0#
#29
b1101 "
b1101 2
b10001 /
b11011 3
1#
#30
1-
b111000010010000 (
1.
b1000010 +
b10 ,
b0 )
b11100 3
b1111000010010000 $
b1111000010010000 '
0#
#31
b1110 "
b1110 2
b10 1
b10 0
b11101 3
1#
#32
0-
b10010 (
0.
b0 +
b0 ,
b10 )
b11110 3
b10010 $
b10010 '
0#
#33
b1111 "
b1111 2
b0 %
b10010 /
b11111 3
1#
#34
1-
b110001100001000 (
b1100 +
b1100 ,
b1 *
b0 )
b100000 3
b1110001100001000 $
b1110001100001000 '
0#
#35
b10000 "
b10000 2
b10 %
b100001 3
1#
#36
0-
b10000 (
b0 +
b0 ,
b10 *
b100010 3
b10000 $
b10000 '
0#
#37
b10001 "
b10001 2
b1 %
b10000 /
b100011 3
1#
#38
1-
b111110000010000 (
1.
b1110000 +
b110000 ,
b100100 3
b1111110000010000 $
b1111110000010000 '
0#
#39
b10010 "
b10010 2
b1 1
b1 0
b100101 3
1#
#40
0-
b10001 (
0.
b0 +
b0 ,
b1 )
b100110 3
b10001 $
b10001 '
0#
#41
b10011 "
b10011 2
b10001 /
b100111 3
1#
#42
1-
b110001100001000 (
b1100 +
b1100 ,
b1 *
b0 )
b101000 3
b1110001100001000 $
b1110001100001000 '
0#
#43
b10100 "
b10100 2
b101001 3
1#
#44
0-
b10010 (
b0 +
b0 ,
b10 *
b10 )
b101010 3
b10010 $
b10010 '
0#
#45
b10101 "
b10101 2
b10 %
b10010 /
b101011 3
1#
#46
1-
b111110000010000 (
1.
b1110000 +
b110000 ,
b0 )
b101100 3
b1111110000010000 $
b1111110000010000 '
0#
#47
b10110 "
b10110 2
b10 1
b10 0
b101101 3
1#
#48
0-
b10000 (
0.
b0 +
b0 ,
b101110 3
b10000 $
b10000 '
0#
#49
b10111 "
b10111 2
b1 %
b10000 /
b101111 3
1#
#50
1-
b110001100001000 (
b1100 +
b1100 ,
b1 *
b110000 3
b1110001100001000 $
b1110001100001000 '
0#
#51
b11000 "
b11000 2
b10 %
b110001 3
1#
#52
0-
b110 (
b0 +
b0 ,
b0 *
b110 )
b110010 3
b110 $
b110 '
0#
#53
b11001 "
b11001 2
bx %
b110 /
b110011 3
1#
#54
1-
b110101010000111 (
b101010 +
b101010 ,
b111 )
b110100 3
b1110101010000111 $
b1110101010000111 '
0#
#55
b110 "
b110 2
b0 0
b110101 3
1#
#56
0-
b10000 (
b0 +
b0 ,
b10 *
b0 )
b110110 3
b10000 $
b10000 '
0#
#57
b111 "
b111 2
b10 %
b10000 /
b110111 3
1#
#58
1-
b111110000010000 (
1.
b1110000 +
b110000 ,
b111000 3
b1111110000010000 $
b1111110000010000 '
0#
#59
b1000 "
b1000 2
b10 0
b111001 3
1#
#60
0-
b100000000000000 (
0.
b0 +
b0 ,
b0 *
b111010 3
b100000000000000 $
b100000000000000 '
0#
#61
b1001 "
b1001 2
b1 %
b100000000000000 /
b111011 3
1#
#62
1-
b110001100001000 (
b1100 +
b1100 ,
b1 *
b111100 3
b1110001100001000 $
b1110001100001000 '
0#
#63
b1010 "
b1010 2
b10 %
b10 !
b10 &
b111101 3
1#
#64
0-
b10000 (
b0 +
b0 ,
b10 *
b111110 3
b10000 $
b10000 '
0#
#65
b1011 "
b1011 2
b10000 /
b111111 3
1#
#66
1-
b111110000010000 (
1.
b1110000 +
b110000 ,
b1000000 3
b1111110000010000 $
b1111110000010000 '
0#
#67
b1100 "
b1100 2
b1000001 3
1#
#68
0-
b10001 (
0.
b0 +
b0 ,
b1 )
b1000010 3
b10001 $
b10001 '
0#
#69
b1101 "
b1101 2
b1 %
b10001 /
b1000011 3
1#
#70
1-
b111000010010000 (
1.
b1000010 +
b10 ,
b0 )
b1000100 3
b1111000010010000 $
b1111000010010000 '
0#
#71
b1110 "
b1110 2
b11 1
b11 0
b1000101 3
1#
#72
0-
b10010 (
0.
b0 +
b0 ,
b10 )
b1000110 3
b10010 $
b10010 '
0#
#73
b1111 "
b1111 2
b10 %
b10010 /
b1000111 3
1#
#74
1-
b110001100001000 (
b1100 +
b1100 ,
b1 *
b0 )
b1001000 3
b1110001100001000 $
b1110001100001000 '
0#
#75
b10000 "
b10000 2
b11 %
b1001001 3
1#
#76
0-
b10000 (
b0 +
b0 ,
b10 *
b1001010 3
b10000 $
b10000 '
0#
#77
b10001 "
b10001 2
b10 %
b10000 /
b1001011 3
1#
#78
1-
b111110000010000 (
1.
b1110000 +
b110000 ,
b1001100 3
b1111110000010000 $
b1111110000010000 '
0#
#79
b10010 "
b10010 2
b10 1
b10 0
b1001101 3
1#
#80
0-
b10001 (
0.
b0 +
b0 ,
b1 )
b1001110 3
b10001 $
b10001 '
0#
#81
b10011 "
b10011 2
b1 %
b10001 /
b1001111 3
1#
#82
1-
b110001100001000 (
b1100 +
b1100 ,
b1 *
b0 )
b1010000 3
b1110001100001000 $
b1110001100001000 '
0#
#83
b10100 "
b10100 2
b10 %
b1010001 3
1#
#84
0-
b10010 (
b0 +
b0 ,
b10 *
b10 )
b1010010 3
b10010 $
b10010 '
0#
#85
b10101 "
b10101 2
b11 %
b10010 /
b1010011 3
1#
#86
1-
b111110000010000 (
1.
b1110000 +
b110000 ,
b0 )
b1010100 3
b1111110000010000 $
b1111110000010000 '
0#
#87
b10110 "
b10110 2
b11 1
b11 0
b1010101 3
1#
#88
0-
b10000 (
0.
b0 +
b0 ,
b1010110 3
b10000 $
b10000 '
0#
#89
b10111 "
b10111 2
b10 %
b10000 /
b1010111 3
1#
#90
1-
b110001100001000 (
b1100 +
b1100 ,
b1 *
b1011000 3
b1110001100001000 $
b1110001100001000 '
0#
#91
b11000 "
b11000 2
b11 %
b1011001 3
1#
#92
0-
b110 (
b0 +
b0 ,
b0 *
b110 )
b1011010 3
b110 $
b110 '
0#
#93
b11001 "
b11001 2
bx %
b110 /
b1011011 3
1#
#94
1-
b110101010000111 (
b101010 +
b101010 ,
b111 )
b1011100 3
b1110101010000111 $
b1110101010000111 '
0#
#95
b110 "
b110 2
b0 0
b1011101 3
1#
#96
0-
b10000 (
b0 +
b0 ,
b10 *
b0 )
b1011110 3
b10000 $
b10000 '
0#
#97
b111 "
b111 2
b11 %
b10000 /
b1011111 3
1#
#98
1-
b111110000010000 (
1.
b1110000 +
b110000 ,
b1100000 3
b1111110000010000 $
b1111110000010000 '
0#
#99
b1000 "
b1000 2
b11 0
b1100001 3
1#
#100
0-
b100000000000000 (
0.
b0 +
b0 ,
b0 *
b1100010 3
b100000000000000 $
b100000000000000 '
0#
#101
b1001 "
b1001 2
b10 %
b100000000000000 /
b1100011 3
1#
#102
1-
b110001100001000 (
b1100 +
b1100 ,
b1 *
b1100100 3
b1110001100001000 $
b1110001100001000 '
0#
#103
b1010 "
b1010 2
b11 %
b11 !
b11 &
b1100101 3
1#
#104
0-
b10000 (
b0 +
b0 ,
b10 *
b1100110 3
b10000 $
b10000 '
0#
#105
b1011 "
b1011 2
b10000 /
b1100111 3
1#
#106
1-
b111110000010000 (
1.
b1110000 +
b110000 ,
b1101000 3
b1111110000010000 $
b1111110000010000 '
0#
#107
b1100 "
b1100 2
b1101001 3
1#
#108
0-
b10001 (
0.
b0 +
b0 ,
b1 )
b1101010 3
b10001 $
b10001 '
0#
#109
b1101 "
b1101 2
b10 %
b10001 /
b1101011 3
1#
#110
1-
b111000010010000 (
1.
b1000010 +
b10 ,
b0 )
b1101100 3
b1111000010010000 $
b1111000010010000 '
0#
#111
b1110 "
b1110 2
b101 1
b101 0
b1101101 3
1#
#112
0-
b10010 (
0.
b0 +
b0 ,
b10 )
b1101110 3
b10010 $
b10010 '
0#
#113
b1111 "
b1111 2
b11 %
b10010 /
b1101111 3
1#
#114
1-
b110001100001000 (
b1100 +
b1100 ,
b1 *
b0 )
b1110000 3
b1110001100001000 $
b1110001100001000 '
0#
#115
b10000 "
b10000 2
b101 %
b1110001 3
1#
#116
0-
b10000 (
b0 +
b0 ,
b10 *
b1110010 3
b10000 $
b10000 '
0#
#117
b10001 "
b10001 2
b11 %
b10000 /
b1110011 3
1#
#118
1-
b111110000010000 (
1.
b1110000 +
b110000 ,
b1110100 3
b1111110000010000 $
b1111110000010000 '
0#
#119
b10010 "
b10010 2
b11 1
b11 0
b1110101 3
1#
#120
0-
b10001 (
0.
b0 +
b0 ,
b1 )
b1110110 3
b10001 $
b10001 '
0#
#121
b10011 "
b10011 2
b10 %
b10001 /
b1110111 3
1#
#122
1-
b110001100001000 (
b1100 +
b1100 ,
b1 *
b0 )
b1111000 3
b1110001100001000 $
b1110001100001000 '
0#
#123
b10100 "
b10100 2
b11 %
b1111001 3
1#
#124
0-
b10010 (
b0 +
b0 ,
b10 *
b10 )
b1111010 3
b10010 $
b10010 '
0#
#125
b10101 "
b10101 2
b101 %
b10010 /
b1111011 3
1#
#126
1-
b111110000010000 (
1.
b1110000 +
b110000 ,
b0 )
b1111100 3
b1111110000010000 $
b1111110000010000 '
0#
#127
b10110 "
b10110 2
b101 1
b101 0
b1111101 3
1#
#128
0-
b10000 (
0.
b0 +
b0 ,
b1111110 3
b10000 $
b10000 '
0#
#129
b10111 "
b10111 2
b11 %
b10000 /
b1111111 3
1#
#130
1-
b110001100001000 (
b1100 +
b1100 ,
b1 *
b10000000 3
b1110001100001000 $
b1110001100001000 '
0#
#131
b11000 "
b11000 2
b101 %
b10000001 3
1#
#132
0-
b110 (
b0 +
b0 ,
b0 *
b110 )
b10000010 3
b110 $
b110 '
0#
#133
b11001 "
b11001 2
bx %
b110 /
b10000011 3
1#
#134
1-
b110101010000111 (
b101010 +
b101010 ,
b111 )
b10000100 3
b1110101010000111 $
b1110101010000111 '
0#
#135
b110 "
b110 2
b0 0
b10000101 3
1#
#136
0-
b10000 (
b0 +
b0 ,
b10 *
b0 )
b10000110 3
b10000 $
b10000 '
0#
#137
b111 "
b111 2
b101 %
b10000 /
b10000111 3
1#
#138
1-
b111110000010000 (
1.
b1110000 +
b110000 ,
b10001000 3
b1111110000010000 $
b1111110000010000 '
0#
#139
b1000 "
b1000 2
b101 0
b10001001 3
1#
#140
0-
b100000000000000 (
0.
b0 +
b0 ,
b0 *
b10001010 3
b100000000000000 $
b100000000000000 '
0#
#141
b1001 "
b1001 2
b11 %
b100000000000000 /
b10001011 3
1#
#142
1-
b110001100001000 (
b1100 +
b1100 ,
b1 *
b10001100 3
b1110001100001000 $
b1110001100001000 '
0#
#143
b1010 "
b1010 2
b101 %
b101 !
b101 &
b10001101 3
1#
#144
0-
b10000 (
b0 +
b0 ,
b10 *
b10001110 3
b10000 $
b10000 '
0#
#145
b1011 "
b1011 2
b10000 /
b10001111 3
1#
#146
1-
b111110000010000 (
1.
b1110000 +
b110000 ,
b10010000 3
b1111110000010000 $
b1111110000010000 '
0#
#147
b1100 "
b1100 2
b10010001 3
1#
#148
0-
b10001 (
0.
b0 +
b0 ,
b1 )
b10010010 3
b10001 $
b10001 '
0#
#149
b1101 "
b1101 2
b11 %
b10001 /
b10010011 3
1#
#150
1-
b111000010010000 (
1.
b1000010 +
b10 ,
b0 )
b10010100 3
b1111000010010000 $
b1111000010010000 '
0#
#151
b1110 "
b1110 2
b1000 1
b1000 0
b10010101 3
1#
#152
0-
b10010 (
0.
b0 +
b0 ,
b10 )
b10010110 3
b10010 $
b10010 '
0#
#153
b1111 "
b1111 2
b101 %
b10010 /
b10010111 3
1#
#154
1-
b110001100001000 (
b1100 +
b1100 ,
b1 *
b0 )
b10011000 3
b1110001100001000 $
b1110001100001000 '
0#
#155
b10000 "
b10000 2
b1000 %
b10011001 3
1#
#156
0-
b10000 (
b0 +
b0 ,
b10 *
b10011010 3
b10000 $
b10000 '
0#
#157
b10001 "
b10001 2
b101 %
b10000 /
b10011011 3
1#
#158
1-
b111110000010000 (
1.
b1110000 +
b110000 ,
b10011100 3
b1111110000010000 $
b1111110000010000 '
0#
#159
b10010 "
b10010 2
b101 1
b101 0
b10011101 3
1#
#160
0-
b10001 (
0.
b0 +
b0 ,
b1 )
b10011110 3
b10001 $
b10001 '
0#
#161
b10011 "
b10011 2
b11 %
b10001 /
b10011111 3
1#
#162
1-
b110001100001000 (
b1100 +
b1100 ,
b1 *
b0 )
b10100000 3
b1110001100001000 $
b1110001100001000 '
0#
#163
b10100 "
b10100 2
b101 %
b10100001 3
1#
#164
0-
b10010 (
b0 +
b0 ,
b10 *
b10 )
b10100010 3
b10010 $
b10010 '
0#
#165
b10101 "
b10101 2
b1000 %
b10010 /
b10100011 3
1#
#166
1-
b111110000010000 (
1.
b1110000 +
b110000 ,
b0 )
b10100100 3
b1111110000010000 $
b1111110000010000 '
0#
#167
b10110 "
b10110 2
b1000 1
b1000 0
b10100101 3
1#
#168
0-
b10000 (
0.
b0 +
b0 ,
b10100110 3
b10000 $
b10000 '
0#
#169
b10111 "
b10111 2
b101 %
b10000 /
b10100111 3
1#
#170
1-
b110001100001000 (
b1100 +
b1100 ,
b1 *
b10101000 3
b1110001100001000 $
b1110001100001000 '
0#
#171
b11000 "
b11000 2
b1000 %
b10101001 3
1#
#172
0-
b110 (
b0 +
b0 ,
b0 *
b110 )
b10101010 3
b110 $
b110 '
0#
#173
b11001 "
b11001 2
bx %
b110 /
b10101011 3
1#
#174
1-
b110101010000111 (
b101010 +
b101010 ,
b111 )
b10101100 3
b1110101010000111 $
b1110101010000111 '
0#
#175
b110 "
b110 2
b0 0
b10101101 3
1#
#176
0-
b10000 (
b0 +
b0 ,
b10 *
b0 )
b10101110 3
b10000 $
b10000 '
0#
#177
b111 "
b111 2
b1000 %
b10000 /
b10101111 3
1#
#178
1-
b111110000010000 (
1.
b1110000 +
b110000 ,
b10110000 3
b1111110000010000 $
b1111110000010000 '
0#
#179
b1000 "
b1000 2
b1000 0
b10110001 3
1#
#180
0-
b100000000000000 (
0.
b0 +
b0 ,
b0 *
b10110010 3
b100000000000000 $
b100000000000000 '
0#
#181
b1001 "
b1001 2
b101 %
b100000000000000 /
b10110011 3
1#
#182
1-
b110001100001000 (
b1100 +
b1100 ,
b1 *
b10110100 3
b1110001100001000 $
b1110001100001000 '
0#
#183
b1010 "
b1010 2
b1000 %
b1000 !
b1000 &
b10110101 3
1#
#184
0-
b10000 (
b0 +
b0 ,
b10 *
b10110110 3
b10000 $
b10000 '
0#
#185
b1011 "
b1011 2
b10000 /
b10110111 3
1#
#186
1-
b111110000010000 (
1.
b1110000 +
b110000 ,
b10111000 3
b1111110000010000 $
b1111110000010000 '
0#
#187
b1100 "
b1100 2
b10111001 3
1#
#188
0-
b10001 (
0.
b0 +
b0 ,
b1 )
b10111010 3
b10001 $
b10001 '
0#
#189
b1101 "
b1101 2
b101 %
b10001 /
b10111011 3
1#
#190
1-
b111000010010000 (
1.
b1000010 +
b10 ,
b0 )
b10111100 3
b1111000010010000 $
b1111000010010000 '
0#
#191
b1110 "
b1110 2
b1101 1
b1101 0
b10111101 3
1#
#192
0-
b10010 (
0.
b0 +
b0 ,
b10 )
b10111110 3
b10010 $
b10010 '
0#
#193
b1111 "
b1111 2
b1000 %
b10010 /
b10111111 3
1#
#194
1-
b110001100001000 (
b1100 +
b1100 ,
b1 *
b0 )
b11000000 3
b1110001100001000 $
b1110001100001000 '
0#
#195
b10000 "
b10000 2
b1101 %
b11000001 3
1#
#196
0-
b10000 (
b0 +
b0 ,
b10 *
b11000010 3
b10000 $
b10000 '
0#
#197
b10001 "
b10001 2
b1000 %
b10000 /
b11000011 3
1#
#198
1-
b111110000010000 (
1.
b1110000 +
b110000 ,
b11000100 3
b1111110000010000 $
b1111110000010000 '
0#
#199
b10010 "
b10010 2
b1000 1
b1000 0
b11000101 3
1#
#200
0-
b10001 (
0.
b0 +
b0 ,
b1 )
b11000110 3
b10001 $
b10001 '
0#
#201
b10011 "
b10011 2
b101 %
b10001 /
b11000111 3
1#
#202
1-
b110001100001000 (
b1100 +
b1100 ,
b1 *
b0 )
b11001000 3
b1110001100001000 $
b1110001100001000 '
0#
#203
b10100 "
b10100 2
b1000 %
b11001001 3
1#
#204
0-
b10010 (
b0 +
b0 ,
b10 *
b10 )
b11001010 3
b10010 $
b10010 '
0#
#205
b10101 "
b10101 2
b1101 %
b10010 /
b11001011 3
1#
#206
1-
b111110000010000 (
1.
b1110000 +
b110000 ,
b0 )
b11001100 3
b1111110000010000 $
b1111110000010000 '
0#
#207
b10110 "
b10110 2
b1101 1
b1101 0
b11001101 3
1#
#208
0-
b10000 (
0.
b0 +
b0 ,
b11001110 3
b10000 $
b10000 '
0#
#209
b10111 "
b10111 2
b1000 %
b10000 /
b11001111 3
1#
#210
1-
b110001100001000 (
b1100 +
b1100 ,
b1 *
b11010000 3
b1110001100001000 $
b1110001100001000 '
0#
#211
b11000 "
b11000 2
b1101 %
b11010001 3
1#
#212
0-
b110 (
b0 +
b0 ,
b0 *
b110 )
b11010010 3
b110 $
b110 '
0#
#213
b11001 "
b11001 2
bx %
b110 /
b11010011 3
1#
#214
1-
b110101010000111 (
b101010 +
b101010 ,
b111 )
b11010100 3
b1110101010000111 $
b1110101010000111 '
0#
#215
b110 "
b110 2
b0 0
b11010101 3
1#
#216
0-
b10000 (
b0 +
b0 ,
b10 *
b0 )
b11010110 3
b10000 $
b10000 '
0#
#217
b111 "
b111 2
b1101 %
b10000 /
b11010111 3
1#
#218
1-
b111110000010000 (
1.
b1110000 +
b110000 ,
b11011000 3
b1111110000010000 $
b1111110000010000 '
0#
#219
b1000 "
b1000 2
b1101 0
b11011001 3
1#
#220
0-
b100000000000000 (
0.
b0 +
b0 ,
b0 *
b11011010 3
b100000000000000 $
b100000000000000 '
0#
#221
b1001 "
b1001 2
b1000 %
b100000000000000 /
b11011011 3
1#
#222
1-
b110001100001000 (
b1100 +
b1100 ,
b1 *
b11011100 3
b1110001100001000 $
b1110001100001000 '
0#
#223
b1010 "
b1010 2
b1101 %
b1101 !
b1101 &
b11011101 3
1#
#224
0-
b10000 (
b0 +
b0 ,
b10 *
b11011110 3
b10000 $
b10000 '
0#
#225
b1011 "
b1011 2
b10000 /
b11011111 3
1#
#226
1-
b111110000010000 (
1.
b1110000 +
b110000 ,
b11100000 3
b1111110000010000 $
b1111110000010000 '
0#
#227
b1100 "
b1100 2
b11100001 3
1#
#228
0-
b10001 (
0.
b0 +
b0 ,
b1 )
b11100010 3
b10001 $
b10001 '
0#
#229
b1101 "
b1101 2
b1000 %
b10001 /
b11100011 3
1#
#230
1-
b111000010010000 (
1.
b1000010 +
b10 ,
b0 )
b11100100 3
b1111000010010000 $
b1111000010010000 '
0#
#231
b1110 "
b1110 2
b10101 1
b10101 0
b11100101 3
1#
#232
0-
b10010 (
0.
b0 +
b0 ,
b10 )
b11100110 3
b10010 $
b10010 '
0#
#233
b1111 "
b1111 2
b1101 %
b10010 /
b11100111 3
1#
#234
1-
b110001100001000 (
b1100 +
b1100 ,
b1 *
b0 )
b11101000 3
b1110001100001000 $
b1110001100001000 '
0#
#235
b10000 "
b10000 2
b10101 %
b11101001 3
1#
#236
0-
b10000 (
b0 +
b0 ,
b10 *
b11101010 3
b10000 $
b10000 '
0#
#237
b10001 "
b10001 2
b1101 %
b10000 /
b11101011 3
1#
#238
1-
b111110000010000 (
1.
b1110000 +
b110000 ,
b11101100 3
b1111110000010000 $
b1111110000010000 '
0#
#239
b10010 "
b10010 2
b1101 1
b1101 0
b11101101 3
1#
#240
0-
b10001 (
0.
b0 +
b0 ,
b1 )
b11101110 3
b10001 $
b10001 '
0#
#241
b10011 "
b10011 2
b1000 %
b10001 /
b11101111 3
1#
#242
1-
b110001100001000 (
b1100 +
b1100 ,
b1 *
b0 )
b11110000 3
b1110001100001000 $
b1110001100001000 '
0#
#243
b10100 "
b10100 2
b1101 %
b11110001 3
1#
#244
0-
b10010 (
b0 +
b0 ,
b10 *
b10 )
b11110010 3
b10010 $
b10010 '
0#
#245
b10101 "
b10101 2
b10101 %
b10010 /
b11110011 3
1#
#246
1-
b111110000010000 (
1.
b1110000 +
b110000 ,
b0 )
b11110100 3
b1111110000010000 $
b1111110000010000 '
0#
#247
b10110 "
b10110 2
b10101 1
b10101 0
b11110101 3
1#
#248
0-
b10000 (
0.
b0 +
b0 ,
b11110110 3
b10000 $
b10000 '
0#
#249
b10111 "
b10111 2
b1101 %
b10000 /
b11110111 3
1#
#250
1-
b110001100001000 (
b1100 +
b1100 ,
b1 *
b11111000 3
b1110001100001000 $
b1110001100001000 '
0#
#251
b11000 "
b11000 2
b10101 %
b11111001 3
1#
#252
0-
b110 (
b0 +
b0 ,
b0 *
b110 )
b11111010 3
b110 $
b110 '
0#
#253
b11001 "
b11001 2
bx %
b110 /
b11111011 3
1#
#254
1-
b110101010000111 (
b101010 +
b101010 ,
b111 )
b11111100 3
b1110101010000111 $
b1110101010000111 '
0#
#255
b110 "
b110 2
b0 0
b11111101 3
1#
#256
0-
b10000 (
b0 +
b0 ,
b10 *
b0 )
b11111110 3
b10000 $
b10000 '
0#
