cpu_16bit/hack/hack.v
module hack (
    input [15:0] instr,
    input clk,

    output reg [14:0] PC,
    output [15:0] OUT
);
  reg [15:0] A;
  reg [15:0] D;

  reg [15:0] RAM[16384:0];

  reg signed [15:0] ALU;

  // ac bit, determines whether a-ins or c-ins
  wire ac = instr[15];

  // the 15-bit value to be loaded to A, if a-ins
  wire [14:0] v = instr[14:0];

  // "a" bit, source of Y operand of alu
  wire a = instr[12];
  // 6-bit c's
  wire [5:0] c = instr[11:6];
  // 3-bit d
  wire [2:0] dest = instr[5:3];
  // 3-bit j
  wire [2:0] jump = instr[2:0];

  // comp, concat a with c's to form a single table like in wiki
  wire [6:0] comp = {a, c};

  wire [15:0] M = RAM[A];  // M "register"

  initial begin
    A  = 0;
    D  = 0;
    PC = 0;

    //$monitor("A:%d | D:%d", A, D);

    #1 $display("R0   | R1   | R2");
    $monitor("%h | %h | %h", RAM[0], RAM[1], RAM[2]);
  end

  assign OUT = D;

  always @(posedge clk) begin

    if (ac == 1'b0) begin
      // a-instruction
      // load v into A register
      A  = v;
      PC = PC + 1;
    end else if (ac == 1'b1) begin
      // c-instruction

      // comp, alu output
      case (comp)
        7'b0101010: ALU = 0;
        7'b0111111: ALU = 1;
        7'b0111010: ALU = -1;
        7'b0001100: ALU = D;
        7'b0110000: ALU = A;
        7'b1110000: ALU = M;
        7'b0001101: ALU = !D;
        7'b0110001: ALU = !A;
        7'b1110001: ALU = !M;
        7'b0001111: ALU = -D;
        7'b0110011: ALU = -A;
        7'b1110011: ALU = -M;
        7'b0011111: ALU = D + 1;
        7'b0110111: ALU = A + 1;
        7'b1110111: ALU = M + 1;
        7'b0001110: ALU = D - 1;
        7'b0110010: ALU = A - 1;
        7'b1110010: ALU = M - 1;
        7'b0000010: ALU = D + A;
        7'b1000010: ALU = D + M;
        7'b0010011: ALU = D - A;
        7'b1010011: ALU = D - M;
        7'b0000111: ALU = A - D;
        7'b1000111: ALU = M - D;
        7'b0000000: ALU = D & A;
        7'b1000000: ALU = D & M;
        7'b0010101: ALU = D | A;
        7'b1010101: ALU = D | M;

        default: ALU = 0;

      endcase

      // dest, where to store this alu output
      case (dest)
        3'b000:  ;
        3'b001:  RAM[A] = ALU;
        3'b010:  D = ALU;
        3'b011: begin
          D = ALU;
          RAM[A] = ALU;
        end
        3'b100:  A = ALU;
        3'b101: begin
          A = ALU;
          RAM[A] = ALU;
        end
        3'b110: begin
          A = ALU;
          D = ALU;
        end
        3'b111: begin
          A = ALU;
          D = ALU;
          RAM[A] = ALU;
        end
        default: ;

      endcase

      // if conditions are satisfied, we "jump" wherever A points to
      case (jump)
        // no jump
        3'b000:  PC = PC + 1;
        // jump if comp > 0
        3'b001:  PC = (ALU > 0) ? A : PC + 1;
        3'b010:  PC = (ALU == 0) ? A : PC + 1;
        3'b011:  PC = (ALU >= 0) ? A : PC + 1;
        3'b100:  PC = (ALU < 0) ? A : PC + 1;
        3'b101:  PC = (ALU != 0) ? A : PC + 1;
        3'b110:  PC = (ALU <= 0) ? A : PC + 1;
        // unconditional jump
        3'b111:  PC = A;
        default: PC = PC + 1;
      endcase

    end

  end

endmodule

cpu_16bit/hack/hack_tb.v
module hack_tb;

  reg clk;
  reg [15:0] instr;
  wire [14:0] PC;
  wire signed [15:0] OUT;

  // ROM
  reg [15:0] ROM[0:255];

  initial begin
    $readmemh("mult.hex", ROM);
    #2 clk = 0;
    // $monitor(OUT);

    for (integer i = 0; i < 255; i++) begin
      #1 clk = ~clk;
      instr = ROM[PC];
    end

    #2 $finish;
    //$monitor("%b", instr);

  end

  hack h0 (
      instr,
      clk,
      PC,
      OUT
  );

  initial begin
    $dumpfile("hack.vcd");
    $dumpvars(0, hack_tb);
  end
endmodule

cpu_16bit/hack/hack.vcd
$date
	Tue Jul 25 21:13:20 2023
$end
$version
	Icarus Verilog
$end
$timescale
	1s
$end
$scope module hack_tb $end
$var wire 15 ! PC [14:0] $end
$var wire 16 " OUT [15:0] $end
$var reg 1 # clk $end
$var reg 16 $ instr [15:0] $end
$scope module h0 $end
$var wire 16 % M [15:0] $end
$var wire 16 & OUT [15:0] $end
$var wire 1 # clk $end
$var wire 16 ' instr [15:0] $end
$var wire 15 ( v [14:0] $end
$var wire 3 ) jump [2:0] $end
$var wire 3 * dest [2:0] $end
$var wire 7 + comp [6:0] $end
$var wire 6 , c [5:0] $end
$var wire 1 - ac $end
$var wire 1 . a $end
$var reg 16 / A [15:0] $end
$var reg 16 0 ALU [15:0] $end
$var reg 16 1 D [15:0] $end
$var reg 15 2 PC [14:0] $end
$upscope $end
$scope begin $ivl_for_loop0 $end
$var integer 32 3 i [31:0] $end
$upscope $end
$upscope $end
$enddefinitions $end
$comment Show the parameter values. $end
$dumpall
$end
#0
$dumpvars
bx 3
b0 2
b0 1
bx 0
b0 /
x.
x-
bx ,
bx +
bx *
bx )
bx (
bx '
b0 &
bx %
bx $
x#
b0 "
b0 !
$end
#2
b0 3
0#
#3
0-
b11 (
0.
b0 +
b0 ,
b0 *
b11 )
b1 3
b11 $
b11 '
1#
#4
b10 3
0#
#5
b1 !
b1 2
b11 /
b11 3
1#
#6
1-
b110110000010000 (
b110000 +
b110000 ,
b10 *
b0 )
b100 3
b1110110000010000 $
b1110110000010000 '
0#
#7
b10 !
b10 2
b11 "
b11 &
b11 1
b11 0
b101 3
1#
#8
0-
b0 (
b0 +
b0 ,
b0 *
b110 3
b0 $
b0 '
0#
#9
b11 !
b11 2
b0 /
b111 3
1#
#10
1-
b110001100001000 (
b1100 +
b1100 ,
b1 *
b1000 3
b1110001100001000 $
b1110001100001000 '
0#
#11
b100 !
b100 2
b11 %
b1001 3
1#
#12
0-
b100 (
b0 +
b0 ,
b0 *
b100 )
b1010 3
b100 $
b100 '
0#
#13
b101 !
b101 2
bx %
b100 /
b1011 3
1#
#14
1-
b110110000010000 (
b110000 +
b110000 ,
b10 *
b0 )
b1100 3
b1110110000010000 $
b1110110000010000 '
0#
#15
b110 !
b110 2
b100 "
b100 &
b100 1
b100 0
b1101 3
1#
#16
0-
b1 (
b0 +
b0 ,
b0 *
b1 )
b1110 3
b1 $
b1 '
0#
#17
b111 !
b111 2
b1 /
b1111 3
1#
#18
1-
b110001100001000 (
b1100 +
b1100 ,
b1 *
b0 )
b10000 3
b1110001100001000 $
b1110001100001000 '
0#
#19
b1000 !
b1000 2
b100 %
b10001 3
1#
#20
0-
b10000 (
b0 +
b0 ,
b10 *
b10010 3
b10000 $
b10000 '
0#
#21
b1001 !
b1001 2
bx %
b10000 /
b10011 3
1#
#22
1-
b110111111001000 (
b111111 +
b111111 ,
b1 *
b10100 3
b1110111111001000 $
b1110111111001000 '
0#
#23
b1010 !
b1010 2
b1 %
b1 0
b10101 3
1#
#24
0-
b10001 (
b0 +
b0 ,
b10 *
b1 )
b10110 3
b10001 $
b10001 '
0#
#25
b1011 !
b1011 2
bx %
b10001 /
b10111 3
1#
#26
1-
b110101010001000 (
b101010 +
b101010 ,
b1 *
b0 )
b11000 3
b1110101010001000 $
b1110101010001000 '
0#
#27
b1100 !
b1100 2
b0 %
b0 0
b11001 3
1#
#28
0-
b10000 (
b0 +
b0 ,
b10 *
b11010 3
b10000 $
b10000 '
0#
#29
b1101 !
b1101 2
b1 %
b10000 /
b11011 3
1#
#30
1-
b111110000010000 (
1.
b1110000 +
b110000 ,
b11100 3
b1111110000010000 $
b1111110000010000 '
0#
#31
b1110 !
b1110 2
b1 "
b1 &
b1 1
b1 0
b11101 3
1#
#32
0-
b1 (
0.
b0 +
b0 ,
b0 *
b1 )
b11110 3
b1 $
b1 '
0#
#33
b1111 !
b1111 2
b100 %
b1 /
b11111 3
1#
#34
1-
b111010011010000 (
1.
b1010011 +
b10011 ,
b10 *
b0 )
b100000 3
b1111010011010000 $
b1111010011010000 '
0#
#35
b10000 !
b10000 2
b1111111111111101 "
b1111111111111101 &
b1111111111111101 1
b1111111111111101 0
b100001 3
1#
#36
0-
b11100 (
0.
b0 +
b0 ,
b11 *
b100 )
b100010 3
b11100 $
b11100 '
0#
#37
b10001 !
b10001 2
bx %
b11100 /
b100011 3
1#
#38
1-
b110001100000001 (
b1100 +
b1100 ,
b0 *
b1 )
b100100 3
b1110001100000001 $
b1110001100000001 '
0#
#39
b10010 !
b10010 2
b100101 3
1#
#40
0-
b10001 (
b0 +
b0 ,
b10 *
b100110 3
b10001 $
b10001 '
0#
#41
b10011 !
b10011 2
b0 %
b10001 /
b100111 3
1#
#42
1-
b111110000010000 (
1.
b1110000 +
b110000 ,
b0 )
b101000 3
b1111110000010000 $
b1111110000010000 '
0#
#43
b10100 !
b10100 2
b0 "
b0 &
b0 1
b0 0
b101001 3
1#
#44
0-
b0 (
0.
b0 +
b0 ,
b0 *
b101010 3
b0 $
b0 '
0#
#45
b10101 !
b10101 2
b11 %
b0 /
b101011 3
1#
#46
1-
b111000010010000 (
1.
b1000010 +
b10 ,
b10 *
b101100 3
b1111000010010000 $
b1111000010010000 '
0#
#47
b10110 !
b10110 2
b11 "
b11 &
b11 1
b11 0
b101101 3
1#
#48
0-
b10001 (
0.
b0 +
b0 ,
b1 )
b101110 3
b10001 $
b10001 '
0#
#49
b10111 !
b10111 2
b0 %
b10001 /
b101111 3
1#
#50
1-
b110001100001000 (
b1100 +
b1100 ,
b1 *
b0 )
b110000 3
b1110001100001000 $
b1110001100001000 '
0#
#51
b11000 !
b11000 2
b11 %
b110001 3
1#
#52
0-
b10000 (
b0 +
b0 ,
b10 *
b110010 3
b10000 $
b10000 '
0#
#53
b11001 !
b11001 2
b1 %
b10000 /
b110011 3
1#
#54
1-
b111110111001000 (
1.
b1110111 +
b110111 ,
b1 *
b110100 3
b1111110111001000 $
b1111110111001000 '
0#
#55
b11010 !
b11010 2
b10 %
b10 0
b110101 3
1#
#56
0-
b1100 (
0.
b0 +
b0 ,
b100 )
b110110 3
b1100 $
b1100 '
0#
#57
b11011 !
b11011 2
bx %
b1100 /
b110111 3
1#
#58
1-
b110101010000111 (
b101010 +
b101010 ,
b0 *
b111 )
b111000 3
b1110101010000111 $
b1110101010000111 '
0#
#59
b1100 !
b1100 2
b0 0
b111001 3
1#
#60
0-
b10000 (
b0 +
b0 ,
b10 *
b0 )
b111010 3
b10000 $
b10000 '
0#
#61
b1101 !
b1101 2
b10 %
b10000 /
b111011 3
1#
#62
1-
b111110000010000 (
1.
b1110000 +
b110000 ,
b111100 3
b1111110000010000 $
b1111110000010000 '
0#
#63
b1110 !
b1110 2
b10 "
b10 &
b10 1
b10 0
b111101 3
1#
#64
0-
b1 (
0.
b0 +
b0 ,
b0 *
b1 )
b111110 3
b1 $
b1 '
0#
#65
b1111 !
b1111 2
b100 %
b1 /
b111111 3
1#
#66
1-
b111010011010000 (
1.
b1010011 +
b10011 ,
b10 *
b0 )
b1000000 3
b1111010011010000 $
b1111010011010000 '
0#
#67
b10000 !
b10000 2
b1111111111111110 "
b1111111111111110 &
b1111111111111110 1
b1111111111111110 0
b1000001 3
1#
#68
0-
b11100 (
0.
b0 +
b0 ,
b11 *
b100 )
b1000010 3
b11100 $
b11100 '
0#
#69
b10001 !
b10001 2
bx %
b11100 /
b1000011 3
1#
#70
1-
b110001100000001 (
b1100 +
b1100 ,
b0 *
b1 )
b1000100 3
b1110001100000001 $
b1110001100000001 '
0#
#71
b10010 !
b10010 2
b1000101 3
1#
#72
0-
b10001 (
b0 +
b0 ,
b10 *
b1000110 3
b10001 $
b10001 '
0#
#73
b10011 !
b10011 2
b11 %
b10001 /
b1000111 3
1#
#74
1-
b111110000010000 (
1.
b1110000 +
b110000 ,
b0 )
b1001000 3
b1111110000010000 $
b1111110000010000 '
0#
#75
b10100 !
b10100 2
b11 "
b11 &
b11 1
b11 0
b1001001 3
1#
#76
0-
b0 (
0.
b0 +
b0 ,
b0 *
b1001010 3
b0 $
b0 '
0#
#77
b10101 !
b10101 2
b0 /
b1001011 3
1#
#78
1-
b111000010010000 (
1.
b1000010 +
b10 ,
b10 *
b1001100 3
b1111000010010000 $
b1111000010010000 '
0#
#79
b10110 !
b10110 2
b110 "
b110 &
b110 1
b110 0
b1001101 3
1#
#80
0-
b10001 (
0.
b0 +
b0 ,
b1 )
b1001110 3
b10001 $
b10001 '
0#
#81
b10111 !
b10111 2
b10001 /
b1001111 3
1#
#82
1-
b110001100001000 (
b1100 +
b1100 ,
b1 *
b0 )
b1010000 3
b1110001100001000 $
b1110001100001000 '
0#
#83
b11000 !
b11000 2
b110 %
b1010001 3
1#
#84
0-
b10000 (
b0 +
b0 ,
b10 *
b1010010 3
b10000 $
b10000 '
0#
#85
b11001 !
b11001 2
b10 %
b10000 /
b1010011 3
1#
#86
1-
b111110111001000 (
1.
b1110111 +
b110111 ,
b1 *
b1010100 3
b1111110111001000 $
b1111110111001000 '
0#
#87
b11010 !
b11010 2
b11 %
b11 0
b1010101 3
1#
#88
0-
b1100 (
0.
b0 +
b0 ,
b100 )
b1010110 3
b1100 $
b1100 '
0#
#89
b11011 !
b11011 2
bx %
b1100 /
b1010111 3
1#
#90
1-
b110101010000111 (
b101010 +
b101010 ,
b0 *
b111 )
b1011000 3
b1110101010000111 $
b1110101010000111 '
0#
#91
b1100 !
b1100 2
b0 0
b1011001 3
1#
#92
0-
b10000 (
b0 +
b0 ,
b10 *
b0 )
b1011010 3
b10000 $
b10000 '
0#
#93
b1101 !
b1101 2
b11 %
b10000 /
b1011011 3
1#
#94
1-
b111110000010000 (
1.
b1110000 +
b110000 ,
b1011100 3
b1111110000010000 $
b1111110000010000 '
0#
#95
b1110 !
b1110 2
b11 "
b11 &
b11 1
b11 0
b1011101 3
1#
#96
0-
b1 (
0.
b0 +
b0 ,
b0 *
b1 )
b1011110 3
b1 $
b1 '
0#
#97
b1111 !
b1111 2
b100 %
b1 /
b1011111 3
1#
#98
1-
b111010011010000 (
1.
b1010011 +
b10011 ,
b10 *
b0 )
b1100000 3
b1111010011010000 $
b1111010011010000 '
0#
#99
b10000 !
b10000 2
b1111111111111111 "
b1111111111111111 &
b1111111111111111 1
b1111111111111111 0
b1100001 3
1#
#100
0-
b11100 (
0.
b0 +
b0 ,
b11 *
b100 )
b1100010 3
b11100 $
b11100 '
0#
#101
b10001 !
b10001 2
bx %
b11100 /
b1100011 3
1#
#102
1-
b110001100000001 (
b1100 +
b1100 ,
b0 *
b1 )
b1100100 3
b1110001100000001 $
b1110001100000001 '
0#
#103
b10010 !
b10010 2
b1100101 3
1#
#104
0-
b10001 (
b0 +
b0 ,
b10 *
b1100110 3
b10001 $
b10001 '
0#
#105
b10011 !
b10011 2
b110 %
b10001 /
b1100111 3
1#
#106
1-
b111110000010000 (
1.
b1110000 +
b110000 ,
b0 )
b1101000 3
b1111110000010000 $
b1111110000010000 '
0#
#107
b10100 !
b10100 2
b110 "
b110 &
b110 1
b110 0
b1101001 3
1#
#108
0-
b0 (
0.
b0 +
b0 ,
b0 *
b1101010 3
b0 $
b0 '
0#
#109
b10101 !
b10101 2
b11 %
b0 /
b1101011 3
1#
#110
1-
b111000010010000 (
1.
b1000010 +
b10 ,
b10 *
b1101100 3
b1111000010010000 $
b1111000010010000 '
0#
#111
b10110 !
b10110 2
b1001 "
b1001 &
b1001 1
b1001 0
b1101101 3
1#
#112
0-
b10001 (
0.
b0 +
b0 ,
b1 )
b1101110 3
b10001 $
b10001 '
0#
#113
b10111 !
b10111 2
b110 %
b10001 /
b1101111 3
1#
#114
1-
b110001100001000 (
b1100 +
b1100 ,
b1 *
b0 )
b1110000 3
b1110001100001000 $
b1110001100001000 '
0#
#115
b11000 !
b11000 2
b1001 %
b1110001 3
1#
#116
0-
b10000 (
b0 +
b0 ,
b10 *
b1110010 3
b10000 $
b10000 '
0#
#117
b11001 !
b11001 2
b11 %
b10000 /
b1110011 3
1#
#118
1-
b111110111001000 (
1.
b1110111 +
b110111 ,
b1 *
b1110100 3
b1111110111001000 $
b1111110111001000 '
0#
#119
b11010 !
b11010 2
b100 %
b100 0
b1110101 3
1#
#120
0-
b1100 (
0.
b0 +
b0 ,
b100 )
b1110110 3
b1100 $
b1100 '
0#
#121
b11011 !
b11011 2
bx %
b1100 /
b1110111 3
1#
#122
1-
b110101010000111 (
b101010 +
b101010 ,
b0 *
b111 )
b1111000 3
b1110101010000111 $
b1110101010000111 '
0#
#123
b1100 !
b1100 2
b0 0
b1111001 3
1#
#124
0-
b10000 (
b0 +
b0 ,
b10 *
b0 )
b1111010 3
b10000 $
b10000 '
0#
#125
b1101 !
b1101 2
b100 %
b10000 /
b1111011 3
1#
#126
1-
b111110000010000 (
1.
b1110000 +
b110000 ,
b1111100 3
b1111110000010000 $
b1111110000010000 '
0#
#127
b1110 !
b1110 2
b100 "
b100 &
b100 1
b100 0
b1111101 3
1#
#128
0-
b1 (
0.
b0 +
b0 ,
b0 *
b1 )
b1111110 3
b1 $
b1 '
0#
#129
b1111 !
b1111 2
b1 /
b1111111 3
1#
#130
1-
b111010011010000 (
1.
b1010011 +
b10011 ,
b10 *
b0 )
b10000000 3
b1111010011010000 $
b1111010011010000 '
0#
#131
b10000 !
b10000 2
b0 "
b0 &
b0 1
b0 0
b10000001 3
1#
#132
0-
b11100 (
0.
b0 +
b0 ,
b11 *
b100 )
b10000010 3
b11100 $
b11100 '
0#
#133
b10001 !
b10001 2
bx %
b11100 /
b10000011 3
1#
#134
1-
b110001100000001 (
b1100 +
b1100 ,
b0 *
b1 )
b10000100 3
b1110001100000001 $
b1110001100000001 '
0#
#135
b10010 !
b10010 2
b10000101 3
1#
#136
0-
b10001 (
b0 +
b0 ,
b10 *
b10000110 3
b10001 $
b10001 '
0#
#137
b10011 !
b10011 2
b1001 %
b10001 /
b10000111 3
1#
#138
1-
b111110000010000 (
1.
b1110000 +
b110000 ,
b0 )
b10001000 3
b1111110000010000 $
b1111110000010000 '
0#
#139
b10100 !
b10100 2
b1001 "
b1001 &
b1001 1
b1001 0
b10001001 3
1#
#140
0-
b0 (
0.
b0 +
b0 ,
b0 *
b10001010 3
b0 $
b0 '
0#
#141
b10101 !
b10101 2
b11 %
b0 /
b10001011 3
1#
#142
1-
b111000010010000 (
1.
b1000010 +
b10 ,
b10 *
b10001100 3
b1111000010010000 $
b1111000010010000 '
0#
#143
b10110 !
b10110 2
b1100 "
b1100 &
b1100 1
b1100 0
b10001101 3
1#
#144
0-
b10001 (
0.
b0 +
b0 ,
b1 )
b10001110 3
b10001 $
b10001 '
0#
#145
b10111 !
b10111 2
b1001 %
b10001 /
b10001111 3
1#
#146
1-
b110001100001000 (
b1100 +
b1100 ,
b1 *
b0 )
b10010000 3
b1110001100001000 $
b1110001100001000 '
0#
#147
b11000 !
b11000 2
b1100 %
b10010001 3
1#
#148
0-
b10000 (
b0 +
b0 ,
b10 *
b10010010 3
b10000 $
b10000 '
0#
#149
b11001 !
b11001 2
b100 %
b10000 /
b10010011 3
1#
#150
1-
b111110111001000 (
1.
b1110111 +
b110111 ,
b1 *
b10010100 3
b1111110111001000 $
b1111110111001000 '
0#
#151
b11010 !
b11010 2
b101 %
b101 0
b10010101 3
1#
#152
0-
b1100 (
0.
b0 +
b0 ,
b100 )
b10010110 3
b1100 $
b1100 '
0#
#153
b11011 !
b11011 2
bx %
b1100 /
b10010111 3
1#
#154
1-
b110101010000111 (
b101010 +
b101010 ,
b0 *
b111 )
b10011000 3
b1110101010000111 $
b1110101010000111 '
0#
#155
b1100 !
b1100 2
b0 0
b10011001 3
1#
#156
0-
b10000 (
b0 +
b0 ,
b10 *
b0 )
b10011010 3
b10000 $
b10000 '
0#
#157
b1101 !
b1101 2
b101 %
b10000 /
b10011011 3
1#
#158
1-
b111110000010000 (
1.
b1110000 +
b110000 ,
b10011100 3
b1111110000010000 $
b1111110000010000 '
0#
#159
b1110 !
b1110 2
b101 "
b101 &
b101 1
b101 0
b10011101 3
1#
#160
0-
b1 (
0.
b0 +
b0 ,
b0 *
b1 )
b10011110 3
b1 $
b1 '
0#
#161
b1111 !
b1111 2
b100 %
b1 /
b10011111 3
1#
#162
1-
b111010011010000 (
1.
b1010011 +
b10011 ,
b10 *
b0 )
b10100000 3
b1111010011010000 $
b1111010011010000 '
0#
#163
b10000 !
b10000 2
b1 "
b1 &
b1 1
b1 0
b10100001 3
1#
#164
0-
b11100 (
0.
b0 +
b0 ,
b11 *
b100 )
b10100010 3
b11100 $
b11100 '
0#
#165
b10001 !
b10001 2
bx %
b11100 /
b10100011 3
1#
#166
1-
b110001100000001 (
b1100 +
b1100 ,
b0 *
b1 )
b10100100 3
b1110001100000001 $
b1110001100000001 '
0#
#167
b11100 !
b11100 2
b10100101 3
1#
#168
0-
b10001 (
b0 +
b0 ,
b10 *
b10100110 3
b10001 $
b10001 '
0#
#169
b11101 !
b11101 2
b1100 %
b10001 /
b10100111 3
1#
#170
1-
b111110000010000 (
1.
b1110000 +
b110000 ,
b0 )
b10101000 3
b1111110000010000 $
b1111110000010000 '
0#
#171
b11110 !
b11110 2
b1100 "
b1100 &
b1100 1
b1100 0
b10101001 3
1#
#172
0-
b10 (
0.
b0 +
b0 ,
b0 *
b10 )
b10101010 3
b10 $
b10 '
0#
#173
b11111 !
b11111 2
bx %
b10 /
b10101011 3
1#
#174
1-
b110001100001000 (
b1100 +
b1100 ,
b1 *
b0 )
b10101100 3
b1110001100001000 $
b1110001100001000 '
0#
#175
b100000 !
b100000 2
b1100 %
b10101101 3
1#
#176
0-
b100000 (
b0 +
b0 ,
b100 *
b10101110 3
b100000 $
b100000 '
0#
#177
b100001 !
b100001 2
bx %
b100000 /
b10101111 3
1#
#178
1-
b110101010000111 (
b101010 +
b101010 ,
b0 *
b111 )
b10110000 3
b1110101010000111 $
b1110101010000111 '
0#
#179
b100000 !
b100000 2
b0 0
b10110001 3
1#
#180
0-
b100000 (
b0 +
b0 ,
b100 *
b0 )
b10110010 3
b100000 $
b100000 '
0#
#181
b100001 !
b100001 2
b10110011 3
1#
#182
1-
b110101010000111 (
b101010 +
b101010 ,
b0 *
b111 )
b10110100 3
b1110101010000111 $
b1110101010000111 '
0#
#183
b100000 !
b100000 2
b10110101 3
1#
#184
0-
b100000 (
b0 +
b0 ,
b100 *
b0 )
b10110110 3
b100000 $
b100000 '
0#
#185
b100001 !
b100001 2
b10110111 3
1#
#186
1-
b110101010000111 (
b101010 +
b101010 ,
b0 *
b111 )
b10111000 3
b1110101010000111 $
b1110101010000111 '
0#
#187
b100000 !
b100000 2
b10111001 3
1#
#188
0-
b100000 (
b0 +
b0 ,
b100 *
b0 )
b10111010 3
b100000 $
b100000 '
0#
#189
b100001 !
b100001 2
b10111011 3
1#
#190
1-
b110101010000111 (
b101010 +
b101010 ,
b0 *
b111 )
b10111100 3
b1110101010000111 $
b1110101010000111 '
0#
#191
b100000 !
b100000 2
b10111101 3
1#
#192
0-
b100000 (
b0 +
b0 ,
b100 *
b0 )
b10111110 3
b100000 $
b100000 '
0#
#193
b100001 !
b100001 2
b10111111 3
1#
#194
1-
b110101010000111 (
b101010 +
b101010 ,
b0 *
b111 )
b11000000 3
b1110101010000111 $
b1110101010000111 '
0#
#195
b100000 !
b100000 2
b11000001 3
1#
#196
0-
b100000 (
b0 +
b0 ,
b100 *
b0 )
b11000010 3
b100000 $
b100000 '
0#
#197
b100001 !
b100001 2
b11000011 3
1#
#198
1-
b110101010000111 (
b101010 +
b101010 ,
b0 *
b111 )
b11000100 3
b1110101010000111 $
b1110101010000111 '
0#
#199
b100000 !
b100000 2
b11000101 3
1#
#200
0-
b100000 (
b0 +
b0 ,
b100 *
b0 )
b11000110 3
b100000 $
b100000 '
0#
#201
b100001 !
b100001 2
b11000111 3
1#
#202
1-
b110101010000111 (
b101010 +
b101010 ,
b0 *
b111 )
b11001000 3
b1110101010000111 $
b1110101010000111 '
0#
#203
b100000 !
b100000 2
b11001001 3
1#
#204
0-
b100000 (
b0 +
b0 ,
b100 *
b0 )
b11001010 3
b100000 $
b100000 '
0#
#205
b100001 !
b100001 2
b11001011 3
1#
#206
1-
b110101010000111 (
b101010 +
b101010 ,
b0 *
b111 )
b11001100 3
b1110101010000111 $
b1110101010000111 '
0#
#207
b100000 !
b100000 2
b11001101 3
1#
#208
0-
b100000 (
b0 +
b0 ,
b100 *
b0 )
b11001110 3
b100000 $
b100000 '
0#
#209
b100001 !
b100001 2
b11001111 3
1#
#210
1-
b110101010000111 (
b101010 +
b101010 ,
b0 *
b111 )
b11010000 3
b1110101010000111 $
b1110101010000111 '
0#
#211
b100000 !
b100000 2
b11010001 3
1#
#212
0-
b100000 (
b0 +
b0 ,
b100 *
b0 )
b11010010 3
b100000 $
b100000 '
0#
#213
b100001 !
b100001 2
b11010011 3
1#
#214
1-
b110101010000111 (
b101010 +
b101010 ,
b0 *
b111 )
b11010100 3
b1110101010000111 $
b1110101010000111 '
0#
#215
b100000 !
b100000 2
b11010101 3
1#
#216
0-
b100000 (
b0 +
b0 ,
b100 *
b0 )
b11010110 3
b100000 $
b100000 '
0#
#217
b100001 !
b100001 2
b11010111 3
1#
#218
1-
b110101010000111 (
b101010 +
b101010 ,
b0 *
b111 )
b11011000 3
b1110101010000111 $
b1110101010000111 '
0#
#219
b100000 !
b100000 2
b11011001 3
1#
#220
0-
b100000 (
b0 +
b0 ,
b100 *
b0 )
b11011010 3
b100000 $
b100000 '
0#
#221
b100001 !
b100001 2
b11011011 3
1#
#222
1-
b110101010000111 (
b101010 +
b101010 ,
b0 *
b111 )
b11011100 3
b1110101010000111 $
b1110101010000111 '
0#
#223
b100000 !
b100000 2
b11011101 3
1#
#224
0-
b100000 (
b0 +
b0 ,
b100 *
b0 )
b11011110 3
b100000 $
b100000 '
0#
#225
b100001 !
b100001 2
b11011111 3
1#
#226
1-
b110101010000111 (
b101010 +
b101010 ,
b0 *
b111 )
b11100000 3
b1110101010000111 $
b1110101010000111 '
0#
#227
b100000 !
b100000 2
b11100001 3
1#
#228
0-
b100000 (
b0 +
b0 ,
b100 *
b0 )
b11100010 3
b100000 $
b100000 '
0#
#229
b100001 !
b100001 2
b11100011 3
1#
#230
1-
b110101010000111 (
b101010 +
b101010 ,
b0 *
b111 )
b11100100 3
b1110101010000111 $
b1110101010000111 '
0#
#231
b100000 !
b100000 2
b11100101 3
1#
#232
0-
b100000 (
b0 +
b0 ,
b100 *
b0 )
b11100110 3
b100000 $
b100000 '
0#
#233
b100001 !
b100001 2
b11100111 3
1#
#234
1-
b110101010000111 (
b101010 +
b101010 ,
b0 *
b111 )
b11101000 3
b1110101010000111 $
b1110101010000111 '
0#
#235
b100000 !
b100000 2
b11101001 3
1#
#236
0-
b100000 (
b0 +
b0 ,
b100 *
b0 )
b11101010 3
b100000 $
b100000 '
0#
#237
b100001 !
b100001 2
b11101011 3
1#
#238
1-
b110101010000111 (
b101010 +
b101010 ,
b0 *
b111 )
b11101100 3
b1110101010000111 $
b1110101010000111 '
0#
#239
b100000 !
b100000 2
b11101101 3
1#
#240
0-
b100000 (
b0 +
b0 ,
b100 *
b0 )
b11101110 3
b100000 $
b100000 '
0#
#241
b100001 !
b100001 2
b11101111 3
1#
#242
1-
b110101010000111 (
b101010 +
b101010 ,
b0 *
b111 )
b11110000 3
b1110101010000111 $
b1110101010000111 '
0#
#243
b100000 !
b100000 2
b11110001 3
1#
#244
0-
b100000 (
b0 +
b0 ,
b100 *
b0 )
b11110010 3
b100000 $
b100000 '
0#
#245
b100001 !
b100001 2
b11110011 3
1#
#246
1-
b110101010000111 (
b101010 +
b101010 ,
b0 *
b111 )
b11110100 3
b1110101010000111 $
b1110101010000111 '
0#
#247
b100000 !
b100000 2
b11110101 3
1#
#248
0-
b100000 (
b0 +
b0 ,
b100 *
b0 )
b11110110 3
b100000 $
b100000 '
0#
#249
b100001 !
b100001 2
b11110111 3
1#
#250
1-
b110101010000111 (
b101010 +
b101010 ,
b0 *
b111 )
b11111000 3
b1110101010000111 $
b1110101010000111 '
0#
#251
b100000 !
b100000 2
b11111001 3
1#
#252
0-
b100000 (
b0 +
b0 ,
b100 *
b0 )
b11111010 3
b100000 $
b100000 '
0#
#253
b100001 !
b100001 2
b11111011 3
1#
#254
1-
b110101010000111 (
b101010 +
b101010 ,
b0 *
b111 )
b11111100 3
b1110101010000111 $
b1110101010000111 '
0#
#255
b100000 !
b100000 2
b11111101 3
1#
#256
0-
b100000 (
b0 +
b0 ,
b100 *
b0 )
b11111110 3
b100000 $
b100000 '
0#
#257
b100001 !
b100001 2
b11111111 3
1#
